altair_cnn/__init__.py
altair_cnn/altair_cnn.py
altair_cnn-0.0.2.dist-info/LICENSE
altair_cnn-0.0.2.dist-info/METADATA
altair_cnn-0.0.2.dist-info/WHEEL
altair_cnn-0.0.2.dist-info/top_level.txt
altair_cnn-0.0.2.dist-info/RECORD
